ncalib/__init__.py
ncalib/nca/__init__.py
ncalib/nca/models/__init__.py
ncalib/nca/models/basic.py
ncalib/nca/models/linear.py
ncalib/nca/models/tiny.py
ncalib/nca/modular_nca.py
ncalib/nca/perception/__init__.py
ncalib/nca/perception/filter.py
ncalib/nca/perception/steerable_filter.py
ncalib/nca/state_updater/__init__.py
ncalib/nca/state_updater/alive_masking.py
ncalib/nca/state_updater/asynchronous_update.py
ncalib/nca/state_updater/noise.py
ncalib/nca/state_updater/simple_update.py
ncalib/samples.py
ncalib/seed_factory/__init__.py
ncalib/seed_factory/genome.py
ncalib/seed_factory/image_seed.py
ncalib/seed_factory/isotropic.py
ncalib/seed_factory/simple_seed.py
ncalib/trainer/__init__.py
ncalib/trainer/batcher/__init__.py
ncalib/trainer/batcher/pool/__init__.py
ncalib/trainer/batcher/pool/eviction_policies/__init__.py
ncalib/trainer/batcher/pool/eviction_policies/loss_policies.py
ncalib/trainer/batcher/pool/eviction_policies/simple_policies.py
ncalib/trainer/batcher/simple.py
ncalib/trainer/combined_trainer.py
ncalib/trainer/dataset/__init__.py
ncalib/trainer/dataset/classification.py
ncalib/trainer/dataset/genome.py
ncalib/trainer/dataset/image_training.py
ncalib/trainer/logger/__init__.py
ncalib/trainer/logger/model.py
ncalib/trainer/logger/tqdm.py
ncalib/trainer/logger/wandb/__init__.py
ncalib/trainer/logger/wandb/metric_logger.py
ncalib/trainer/loss_function/__init__.py
ncalib/trainer/loss_function/auxiliary_loss.py
ncalib/trainer/loss_function/image_target_loss.py
ncalib/trainer/stopping_criterion/__init__.py
ncalib/trainer/stopping_criterion/simple_criteria.py
ncalib/trainer/target/__init__.py
ncalib/trainer/target/single_image.py
ncalib/utils/__init__.py
ncalib/utils/color_space.py
ncalib/utils/defaults.py
ncalib/utils/image.py
ncalib/utils/kernels.py
ncalib/utils/nca.py
ncalib/utils/torch_helper.py
ncalib/utils/transforms.py
ncalib/utils/utils.py
ncalib/utils/wandb.py
ncalib/visualization/__init__.py
ncalib/visualization/gui/__init__.py
ncalib-0.1.2.dist-info/WHEEL
ncalib-0.1.2.dist-info/METADATA
ncalib-0.1.2.dist-info/RECORD
