Metadata-Version: 2.4
Name: ncalib
Version: 0.1.2
Summary: Modular Python Library for Neural Cellular Automata
Author: Dominik Woiwode
Author-email: Dominik Woiwode <woiwode@tnt.uni-hannover.de>
License-Expression: MIT
Classifier: Programming Language :: Python :: 3
Classifier: License :: OSI Approved :: MIT License
Classifier: Operating System :: OS Independent
Requires-Dist: flatten-dict>=0.4.2
Requires-Dist: gitpython>=3.1.45
Requires-Dist: hydra-core>=1.3.2
Requires-Dist: importlib-metadata>=8.7.0
Requires-Dist: jaxtyping>=0.2.36
Requires-Dist: lightning>=2.5.2
Requires-Dist: matplotlib>=3.9.4
Requires-Dist: numpy>=2.0.2
Requires-Dist: omegaconf>=2.3.0
Requires-Dist: opencv-python>=4.11.0.86
Requires-Dist: tensordict>=0.9.1
Requires-Dist: torch>=2.8.0
Requires-Dist: torchvision>=0.23.0
Requires-Dist: tqdm>=4.67.1
Requires-Dist: wandb ; extra == 'wandb'
Requires-Dist: hydra-slurm-rich-launcher ; extra == 'wandb'
Requires-Python: >=3.9
Provides-Extra: wandb
